odoo/addons/hr_contract_rate/README.rst
odoo/addons/hr_contract_rate/__init__.py
odoo/addons/hr_contract_rate/__manifest__.py
odoo/addons/hr_contract_rate/hooks.py
odoo/addons/hr_contract_rate/i18n/hr_contract_rate.pot
odoo/addons/hr_contract_rate/i18n/it.po
odoo/addons/hr_contract_rate/models/__init__.py
odoo/addons/hr_contract_rate/models/hr_contract.py
odoo/addons/hr_contract_rate/readme/CONTRIBUTORS.rst
odoo/addons/hr_contract_rate/readme/DESCRIPTION.rst
odoo/addons/hr_contract_rate/readme/USAGE.rst
odoo/addons/hr_contract_rate/static/description/icon.png
odoo/addons/hr_contract_rate/static/description/index.html
odoo/addons/hr_contract_rate/tests/__init__.py
odoo/addons/hr_contract_rate/tests/test_hr_contract_rate.py
odoo/addons/hr_contract_rate/views/hr_contract.xml
odoo12_addon_hr_contract_rate-12.0.1.0.0.99.dev10.dist-info/METADATA
odoo12_addon_hr_contract_rate-12.0.1.0.0.99.dev10.dist-info/WHEEL
odoo12_addon_hr_contract_rate-12.0.1.0.0.99.dev10.dist-info/top_level.txt
odoo12_addon_hr_contract_rate-12.0.1.0.0.99.dev10.dist-info/RECORD
